<?xml version="1.0" encoding="utf-8"?>
<!DOCTYPE hibernate-mapping PUBLIC "-//Hibernate/Hibernate Mapping DTD 3.0//EN"
"http://www.hibernate.org/dtd/hibernate-mapping-3.0.dtd">
<!-- 
    Mapping file autogenerated by MyEclipse Persistence Tools
-->
<hibernate-mapping>
    <class name="cn.repair.bean.RepairLog" table="repair_log">
        <id name="logId" type="java.lang.Integer">
            <column name="log_id" />
            <generator class="increment" />
        </id>
        <property name="itemId" type="java.lang.Integer">
            <column name="item_id" />
        </property>
        <property name="userId" type="java.lang.Integer">
            <column name="user_id" />
        </property>
        <property name="logTime" type="java.lang.String">
            <column name="log_time" length="20" />
        </property>
        <property name="logType" type="java.lang.Integer">
            <column name="log_type" />
        </property>
        <property name="logMsg" type="java.lang.String">
            <column name="log_msg" length="50" />
        </property>
    </class>
</hibernate-mapping>
